modelopt/__init__.py
modelopt/deploy/__init__.py
modelopt/deploy/llm/__init__.py
modelopt/deploy/llm/generate.py
modelopt/onnx/__init__.py
modelopt/onnx/logging_config.py
modelopt/onnx/op_types.py
modelopt/onnx/trt_utils.py
modelopt/onnx/utils.py
modelopt/onnx/autocast/__init__.py
modelopt/onnx/autocast/__main__.py
modelopt/onnx/autocast/convert.py
modelopt/onnx/autocast/graphsanitizer.py
modelopt/onnx/autocast/logging_config.py
modelopt/onnx/autocast/nodeclassifier.py
modelopt/onnx/autocast/precisionconverter.py
modelopt/onnx/autocast/referencerunner.py
modelopt/onnx/autocast/utils.py
modelopt/onnx/export/__init__.py
modelopt/onnx/export/base_exporter.py
modelopt/onnx/export/fp8_exporter.py
modelopt/onnx/export/int4_exporter.py
modelopt/onnx/export/int8_exporter.py
modelopt/onnx/export/mxfp8_exporter.py
modelopt/onnx/export/nvfp4_exporter.py
modelopt/onnx/llm_export_utils/__init__.py
modelopt/onnx/llm_export_utils/export_utils.py
modelopt/onnx/llm_export_utils/quantization_utils.py
modelopt/onnx/llm_export_utils/surgeon_utils.py
modelopt/onnx/quantization/__init__.py
modelopt/onnx/quantization/__main__.py
modelopt/onnx/quantization/calib_utils.py
modelopt/onnx/quantization/extensions.py
modelopt/onnx/quantization/fp8.py
modelopt/onnx/quantization/graph_utils.py
modelopt/onnx/quantization/gs_patching.py
modelopt/onnx/quantization/int4.py
modelopt/onnx/quantization/int8.py
modelopt/onnx/quantization/operators.py
modelopt/onnx/quantization/ort_patching.py
modelopt/onnx/quantization/ort_utils.py
modelopt/onnx/quantization/partitioning.py
modelopt/onnx/quantization/qdq_utils.py
modelopt/onnx/quantization/quant_utils.py
modelopt/onnx/quantization/quantize.py
modelopt/onnx/quantization/src/modelopt_round_and_pack_ext.cpp
modelopt/torch/__init__.py
modelopt/torch/_deploy/__init__.py
modelopt/torch/_deploy/compilation.py
modelopt/torch/_deploy/device_model.py
modelopt/torch/_deploy/profiling.py
modelopt/torch/_deploy/_runtime/__init__.py
nvidia_modelopt-0.41.0.dist-info/licenses/LICENSE_HEADER
nvidia_modelopt-0.41.0.dist-info/METADATA
nvidia_modelopt-0.41.0.dist-info/WHEEL
nvidia_modelopt-0.41.0.dist-info/top_level.txt
nvidia_modelopt-0.41.0.dist-info/RECORD
